hsr_sendmessage/__init__.py
hsr_sendmessage-0.2.0.dist-info/WHEEL
hsr_sendmessage-0.2.0.dist-info/entry_points.txt
hsr_sendmessage-0.2.0.dist-info/METADATA
hsr_sendmessage-0.2.0.dist-info/RECORD
