Metadata-Version: 2.3
Name: hsr-sendmessage
Version: 0.2.0
Summary: Add your description here
Author: asryshuang
Author-email: asryshuang <asryshuang@tencent.com>
Requires-Dist: mcp[cli]>=1.25.0
Requires-Python: >=3.11
